setup.py
lulfglkvgzpconz/__init__.py
lulfglkvgzpconz/cli.py
lulfglkvgzpconz.egg-info/PKG-INFO
lulfglkvgzpconz.egg-info/SOURCES.txt
lulfglkvgzpconz.egg-info/dependency_links.txt
lulfglkvgzpconz.egg-info/entry_points.txt
lulfglkvgzpconz.egg-info/top_level.txt